confounds/__init__.py
confounds/_version.py
confounds/base.py
confounds/combat.py
confounds/harmonize.py
confounds/metrics.py
confounds/stratify.py
confounds/utils.py
confounds/visualize.py
confounds-0.1.3.dist-info/AUTHORS.rst
confounds-0.1.3.dist-info/LICENSE
confounds-0.1.3.dist-info/METADATA
confounds-0.1.3.dist-info/WHEEL
confounds-0.1.3.dist-info/top_level.txt
confounds-0.1.3.dist-info/RECORD
