Metadata-Version: 2.1
Name: confounds
Version: 0.1.3
Summary: Conquering confounds and covariates in machine learning
Requires-Dist: numpy
Requires-Dist: scikit-learn
Requires-Dist: seaborn
